ab_methods/__init__.py
ab_methods/ab_methods.py
ab_methods-0.1.0.dist-info/METADATA
ab_methods-0.1.0.dist-info/WHEEL
ab_methods-0.1.0.dist-info/top_level.txt
ab_methods-0.1.0.dist-info/RECORD
