Metadata-Version: 2.4
Name: ab_methods
Version: 0.1.0
Summary: A/B testing tools for analysts
Requires-Python: >=3.8
Requires-Dist: numpy>=1.22
Requires-Dist: pandas>=1.5
Requires-Dist: scipy>=1.10
Requires-Dist: matplotlib>=3.7
Requires-Dist: tqdm>=4.65
